{
    "seadata": [
        {
            "date": "2026년 2월 15일",
            "news_image_url_1": "./image/news_20260215_001.jpg",
            "news_image_url_2": "./image/news_20260215_002.jpg",
            "news_image_url_3": "./image/news_20260215_003.jpg",
            "news_image_url_4": "./image/news_20260215_004.jpg",
            "link_url": "https://sudsy-curiosity-466.notion.site/2d5d58c3dc9880d5ae0bcf644cc5dea9?v=2d5d58c3dc9881da9e83000c2918e700&p=307d58c3dc98800b8d37f2087b5b17b3&pm=s"
        }
    ]
}
